sharelatex_versioning/__init__.py
sharelatex_versioning/classes/__init__.py
sharelatex_versioning/classes/cache.py
sharelatex_versioning/classes/configuration.py
sharelatex_versioning/logic/__init__.py
sharelatex_versioning/logic/download_zip.py
sharelatex_versioning/logic/hash_file.py
sharelatex_versioning/utils/__init__.py
sharelatex_versioning/utils/password_handling.py
sharelatex_versioning-0.1.15.dist-info/METADATA
sharelatex_versioning-0.1.15.dist-info/WHEEL
sharelatex_versioning-0.1.15.dist-info/entry_points.txt
sharelatex_versioning-0.1.15.dist-info/licenses/LICENSE
sharelatex_versioning-0.1.15.dist-info/RECORD
