Metadata-Version: 2.4
Name: sharelatex-versioning
Version: 0.1.15
Summary: Tool to backup ShareLaTeX files locally.
Project-URL: Repository, https://github.com/pstoeckle/ShareLaTeX-Versioning.git
Author-email: Patrick Stöckle <patrick.stoeckle@posteo.de>
Maintainer-email: Patrick Stöckle <patrick.stoeckle@posteo.de>
License-Expression: Apache-2.0
License-File: LICENSE
Requires-Python: <4.0,>=3.11
Requires-Dist: bs4==0.0.2
Requires-Dist: keyring==25.6.0
Requires-Dist: requests==2.32.3
Requires-Dist: typer==0.15.2
